AoE2ScenarioRms/__init__.py
AoE2ScenarioRms/version.py
AoE2ScenarioRms/core/__init__.py
AoE2ScenarioRms/core/aoe2_scenario_rms.py
AoE2ScenarioRms/debug/__init__.py
AoE2ScenarioRms/debug/apply_all_visible.py
AoE2ScenarioRms/debug/apply_debug.py
AoE2ScenarioRms/debug/apply_no_clutter.py
AoE2ScenarioRms/debug/apply_state_as_black.py
AoE2ScenarioRms/debug/apply_xs_print.py
AoE2ScenarioRms/enums/__init__.py
AoE2ScenarioRms/enums/grouping_method.py
AoE2ScenarioRms/enums/tile_level.py
AoE2ScenarioRms/enums/internal/__init__.py
AoE2ScenarioRms/enums/internal/xs_key.py
AoE2ScenarioRms/errors/__init__.py
AoE2ScenarioRms/errors/exceptions.py
AoE2ScenarioRms/errors/warnings.py
AoE2ScenarioRms/flags/__init__.py
AoE2ScenarioRms/flags/object_clear.py
AoE2ScenarioRms/flags/object_marks.py
AoE2ScenarioRms/flags/terrain_mark.py
AoE2ScenarioRms/rms/__init__.py
AoE2ScenarioRms/rms/rms_config.py
AoE2ScenarioRms/rms/rms_feature.py
AoE2ScenarioRms/rms/create_object/__init__.py
AoE2ScenarioRms/rms/create_object/create_object_config.py
AoE2ScenarioRms/rms/create_object/create_object_feature.py
AoE2ScenarioRms/util/__init__.py
AoE2ScenarioRms/util/data.py
AoE2ScenarioRms/util/grid_map.py
AoE2ScenarioRms/util/grid_map_factory.py
AoE2ScenarioRms/util/locator.py
AoE2ScenarioRms/util/scenario_util.py
AoE2ScenarioRms/util/tile_util.py
AoE2ScenarioRms/util/unit_util.py
AoE2ScenarioRms/util/xs_container.py
AoE2ScenarioRms/util/xs_util.py
AoE2ScenarioRms/xs/debug.xs
AoE2ScenarioRms/xs/main.xs
AoE2ScenarioRms/xs/random.xs
AoE2ScenarioRms/xs/snippets/debug_print_info.xs
aoe2scenariorms-0.3.10.dist-info/licenses/LICENSE
aoe2scenariorms-0.3.10.dist-info/METADATA
aoe2scenariorms-0.3.10.dist-info/WHEEL
aoe2scenariorms-0.3.10.dist-info/top_level.txt
aoe2scenariorms-0.3.10.dist-info/RECORD
