Metadata-Version: 2.4
Name: AoE2ScenarioRms
Version: 0.3.10
Summary: Add replay-ability to scenarios through random resource placement using triggers & XS!
Author-email: Kerwin Sneijders <ksneijders-dev@hotmail.com>
License: MIT License
Project-URL: Homepage, https://github.com/KSneijders/AoE2ScenarioRms
Project-URL: Bug Tracker, https://github.com/KSneijders/AoE2ScenarioRms/issues
Project-URL: Examples, https://github.com/KSneijders/AoE2ScenarioRms/tree/main/examples
Project-URL: Changelog, https://github.com/KSneijders/AoE2ScenarioRms/blob/main/CHANGELOG.md
Classifier: Programming Language :: Python :: 3
Classifier: License :: OSI Approved :: MIT License
Classifier: Operating System :: OS Independent
Requires-Python: >=3.11
License-File: LICENSE
Requires-Dist: AoE2ScenarioParser>=0.3.0
Dynamic: license-file
